ruccent/__init__.py
ruccent/accent.mdl
ruccent/accent.py
ruccent-1.0.2.dist-info/LICENSE
ruccent-1.0.2.dist-info/METADATA
ruccent-1.0.2.dist-info/WHEEL
ruccent-1.0.2.dist-info/top_level.txt
ruccent-1.0.2.dist-info/RECORD
