Metadata-Version: 2.1
Name: ruccent
Version: 1.0.2
Summary: Pure Python, no dependencies, simple word accent setter, based on ngram model.
Home-page: https://github.com/lecronru/ruccent
Author: Lecron
Author-email: lecronru@gmail.com
License: MIT License
Keywords: natural language processing,russian
Platform: UNKNOWN
Classifier: License :: OSI Approved :: MIT License
Classifier: Programming Language :: Python :: 3.10
License-File: LICENSE
